ingress2qsirecon/__init__.py
ingress2qsirecon/cli/__init__.py
ingress2qsirecon/cli/main.py
ingress2qsirecon/cli/parser.py
ingress2qsirecon/data/__init__.py
ingress2qsirecon/data/bids_scaffold/README
ingress2qsirecon/data/bids_scaffold/dataset_description.json
ingress2qsirecon/utils/__init__.py
ingress2qsirecon/utils/functions.py
ingress2qsirecon/utils/interfaces.py
ingress2qsirecon/utils/workflows.py
ingress2qsirecon-0.2.3.dist-info/LICENSE.txt
ingress2qsirecon-0.2.3.dist-info/METADATA
ingress2qsirecon-0.2.3.dist-info/WHEEL
ingress2qsirecon-0.2.3.dist-info/entry_points.txt
ingress2qsirecon-0.2.3.dist-info/RECORD
